Workbook

Sheet 3.8.1 Exchange Risk - CAD
A1: Date | B1: Exchange Rate Returns | C1: GDP Growth - CAD | D1: GDP Growth - USD | E1: {='3.8 Data - CAD#USD '!J2:L271} -> Interest Rate Differential | F1: Inflation Rate Differential | G1: Account Balance Differential | I1: SUMMARY OUTPUT
A2: 37134 | C2: ='3.8 Data - CAD#USD '!F3/100 -> 0.014604127 | D2: ='3.8 Data - CAD#USD '!G3/100 -> 0.012591457 | E2: 0.005596046 | F2: 0.001057445 | G2: 0.053440442
A3: 37164 | B3: ='Final Data'!I3 -> 0.00052900723 | C3: ='3.8 Data - CAD#USD '!F4/100 -> 0.012615182 | D3: ='3.8 Data - CAD#USD '!G4/100 -> 0.0114197 | E3: 0.00582 | F3: 0.000147109 | G3: 0.053440441 | I3: Regression Statistics
A4: 37195 | B4: ='Final Data'!I4 -> 0.012160733 | C4: ='3.8 Data - CAD#USD '!F5/100 -> 0.012615182 | D4: ='3.8 Data - CAD#USD '!G5/100 -> 0.0114197 | E4: 0.006679455 | F4: -0.002585142 | G4: 0.044425445 | I4: Multiple R | J4: 0.22473418
A5: 37225 | B5: ='Final Data'!I5 -> 0.011056939 | C5: ='3.8 Data - CAD#USD '!F6/100 -> 0.012615182 | D5: ='3.8 Data - CAD#USD '!G6/100 -> 0.0114197 | E5: 0.005263319 | F5: -0.01274548 | G5: 0.044425445 | I5: R Square | J5: 0.05050545
A6: 37256 | B6: ='Final Data'!I6 -> 0.0053388444 | C6: ='3.8 Data - CAD#USD '!F7/100 -> 0.013412488 | D6: ='3.8 Data - CAD#USD '!G7/100 -> 0.010529206 | E6: 0.003209209 | F6: -0.0088200605 | G6: 0.044425445 | I6: Adjusted R Square | J6: 0.032385325
A7: 37287 | B7: ='Final Data'!I7 -> 0.029892934 | C7: ='3.8 Data - CAD#USD '!F8/100 -> 0.013412488 | D7: ='3.8 Data - CAD#USD '!G8/100 -> 0.010529206 | E7: 0.0031 | F7: 0.001470816 | G7: 0.06252773 | I7: Standard Error | J7: 0.022019906
A8: 37315 | B8: ='Final Data'!I8 -> -0.0089820359 | C8: ='3.8 Data - CAD#USD '!F9/100 -> 0.013412488 | D8: ='3.8 Data - CAD#USD '!G9/100 -> 0.010529206 | E8: 0.00410001 | F8: 0.004116256 | G8: 0.062527728 | I8: Observations | J8: 268
A9: 37346 | B9: ='Final Data'!I9 -> -0.0045317221 | C9: ='3.8 Data - CAD#USD '!F10/100 -> 0.014917686 | D9: ='3.8 Data - CAD#USD '!G10/100 -> 0.013270985 | E9: 0.003830006 | F9: 0.0038791 | G9: 0.062527728
A10: 37376 | B10: ='Final Data'!I10 -> -0.028915866 | C10: ='3.8 Data - CAD#USD '!F11/100 -> 0.014917686 | D10: ='3.8 Data - CAD#USD '!G11/100 -> 0.013270985 | E10: 0.004477272 | F10: 0.000942525 | G10: 0.060764595 | I10: ANOVA
A11: 37407 | B11: ='Final Data'!I11 -> -0.029342825 | C11: ='3.8 Data - CAD#USD '!F12/100 -> 0.014917686 | D11: ='3.8 Data - CAD#USD '!G12/100 -> 0.013270985 | E11: 0.00431644 | F11: -0.00224568 | G11: 0.060764595 | J11: df | K11: SS | L11: MS | M11: F | N11: Significance F
A12: 37437 | B12: ='Final Data'!I12 -> -0.05097934 | C12: ='3.8 Data - CAD#USD '!F13/100 -> 0.015328482 | D12: ='3.8 Data - CAD#USD '!G13/100 -> 0.01324841 | E12: 0.004975017 | F12: 0.001502972 | G12: 0.060764595 | I12: Regression | J12: 5 | K12: 0.0067573744 | L12: 0.0013514749 | M12: 2.7872573 | N12: 0.017952287
A13: 37468 | B13: ='Final Data'!I13 -> 0.012251437 | C13: ='3.8 Data - CAD#USD '!F14/100 -> 0.015328482 | D13: ='3.8 Data - CAD#USD '!G14/100 -> 0.01324841 | E13: 0.006339605 | F13: 0.007769968 | G13: 0.055863964 | I13: Residual | J13: 262 | K13: 0.12703758 | L13: 0.00048487626
A14: 37499 | B14: ='Final Data'!I14 -> -0.0040033516 | C14: ='3.8 Data - CAD#USD '!F15/100 -> 0.015328482 | D14: ='3.8 Data - CAD#USD '!G15/100 -> 0.01324841 | E14: 0.008632035 | F14: 0.00798352 | G14: 0.055863963 | I14: Total | J14: 267 | K14: 0.13379495
A15: 37529 | B15: ='Final Data'!I15 -> -0.0010282296 | C15: ='3.8 Data - CAD#USD '!F16/100 -> 0.01658465 | D15: ='3.8 Data - CAD#USD '!G16/100 -> 0.01465356 | E15: 0.010155003 | F15: 0.009230353 | G15: 0.055863964
A16: 37560 | B16: ='Final Data'!I16 -> -0.0021521475 | C16: ='3.8 Data - CAD#USD '!F17/100 -> 0.01658465 | D16: ='3.8 Data - CAD#USD '!G17/100 -> 0.01465356 | E16: 0.01191186 | F16: 0.012349707 | G16: 0.057476415 | J16: Coefficients | K16: Standard Error | L16: t Stat | M16: P-value | N16: Lower 95% | O16: Upper 95% | P16: Lower 95.0% | Q16: Upper 95.0%
A17: 37590 | B17: ='Final Data'!I17 -> -0.0021567892 | C17: ='3.8 Data - CAD#USD '!F18/100 -> 0.01658465 | D17: ='3.8 Data - CAD#USD '!G18/100 -> 0.01465356 | E17: 0.010478156 | F17: 0.020585932 | G17: 0.057476415 | I17: Intercept | J17: -0.0035003532 | K17: 0.0028113505 | L17: -1.2450789 | M17: 0.2142152 | N17: -0.0090360701 | O17: 0.0020353637 | P17: -0.0090360701 | Q17: 0.0020353637
A18: 37621 | B18: ='Final Data'!I18 -> -0.042853115 | C18: ='3.8 Data - CAD#USD '!F19/100 -> 0.016521399 | D18: ='3.8 Data - CAD#USD '!G19/100 -> 0.014410507 | E18: 0.009351187 | F18: 0.014091947 | G18: 0.057476415 | I18: =C1 -> GDP Growth - CAD | J18: 0.10542628 | K18: 0.36264397 | L18: 0.29071566 | M18: 0.77149879 | N18: -0.60864135 | O18: 0.81949391 | P18: -0.60864135 | Q18: 0.81949391
A19: 37652 | B19: ='Final Data'!I19 -> -0.019047619 | C19: ='3.8 Data - CAD#USD '!F20/100 -> 0.016521399 | D19: ='3.8 Data - CAD#USD '!G20/100 -> 0.014410507 | E19: 0.009152375 | F19: 0.016258307 | G19: 0.060118679 | I19: =D1 -> GDP Growth - USD | J19: 0.24446982 | K19: 0.40193939 | L19: 0.60822557 | M19: 0.54356477 | N19: -0.54697285 | O19: 1.0359125 | P19: -0.54697285 | Q19: 1.0359125
A20: 37680 | B20: ='Final Data'!I20 -> -0.0020018016 | C20: ='3.8 Data - CAD#USD '!F21/100 -> 0.016521399 | D20: ='3.8 Data - CAD#USD '!G21/100 -> 0.014410507 | E20: 0.011078952 | F20: 0.014271092 | G20: 0.060118678 | I20: =E1 -> Interest Rate Differential | J20: 0.011387074 | K20: 0.35217513 | L20: 0.032333556 | M20: 0.97423067 | N20: -0.68206678 | O20: 0.70484093 | P20: -0.68206678 | Q20: 0.70484093
A21: 37711 | B21: ='Final Data'!I21 -> -0.0065189048 | C21: ='3.8 Data - CAD#USD '!F22/100 -> 0.015305616 | D21: ='3.8 Data - CAD#USD '!G22/100 -> 0.013888995 | E21: 0.011900003 | F21: 0.012258139 | G21: 0.060118679 | I21: =F1 -> Inflation Rate Differential | J21: -0.45454713 | K21: 0.18260713 | L21: -2.489208 | M21: 0.013423895 | N21: -0.81411147 | O21: -0.094982793 | P21: -0.81411147 | Q21: -0.094982793
A22: 37741 | B22: ='Final Data'!I22 -> -0.018877448 | C22: ='3.8 Data - CAD#USD '!F23/100 -> 0.015305616 | D22: ='3.8 Data - CAD#USD '!G23/100 -> 0.013888995 | E22: 0.010933344 | F22: 0.006389444 | G22: 0.048791456 | I22: =G1 -> Account Balance Differential | J22: -0.11754209 | K22: 0.049565582 | L22: -2.3714458 | M22: 0.018442093 | N22: -0.21513968 | O22: -0.019944501 | P22: -0.21513968 | Q22: -0.019944501
A23: 37772 | B23: ='Final Data'!I23 -> -0.040333368 | C23: ='3.8 Data - CAD#USD '!F24/100 -> 0.015305616 | D23: ='3.8 Data - CAD#USD '!G24/100 -> 0.013888995 | E23: 0.011169519 | F23: 0.008221491 | G23: 0.048791456
A24: 37802 | B24: ='Final Data'!I24 -> 0.015653479 | C24: ='3.8 Data - CAD#USD '!F25/100 -> 0.014153176 | D24: ='3.8 Data - CAD#USD '!G25/100 -> 0.014350123 | E24: 0.009538095 | F24: 0.007620738 | G24: 0.048791456
A25: 37833 | B25: ='Final Data'!I25 -> 0.022801647 | C25: ='3.8 Data - CAD#USD '!F26/100 -> 0.014153176 | D25: ='3.8 Data - CAD#USD '!G26/100 -> 0.014350123 | E25: 0.007150209 | F25: 0.001378581 | G25: 0.061583761
A26: 37864 | B26: ='Final Data'!I26 -> 0.012488389 | C26: ='3.8 Data - CAD#USD '!F27/100 -> 0.014153176 | D26: ='3.8 Data - CAD#USD '!G27/100 -> 0.014350123 | E26: 0.004567619 | F26: -0.001306543 | G26: 0.061583761
A27: 37894 | B27: ='Final Data'!I27 -> -0.05351682 | C27: ='3.8 Data - CAD#USD '!F28/100 -> 0.013275173 | D27: ='3.8 Data - CAD#USD '!G28/100 -> 0.01617407 | E27: 0.004828553 | F27: -0.001957867 | G27: 0.061583761
A28: 37925 | B28: ='Final Data'!I28 -> -0.0012924071 | C28: ='3.8 Data - CAD#USD '!F29/100 -> 0.013275173 | D28: ='3.8 Data - CAD#USD '!G29/100 -> 0.01617407 | E28: 0.005250192 | F28: -0.004624801 | G28: 0.061029838
A29: 37955 | B29: ='Final Data'!I29 -> -0.027175671 | C29: ='3.8 Data - CAD#USD '!F30/100 -> 0.013275173 | D29: ='3.8 Data - CAD#USD '!G30/100 -> 0.01617407 | E29: 0.005494446 | F29: -0.004519959 | G29: 0.061029838
A30: 37986 | B30: ='Final Data'!I30 -> -0.036470458 | C30: ='3.8 Data - CAD#USD '!F31/100 -> 0.013533513 | D30: ='3.8 Data - CAD#USD '!G31/100 -> 0.017435617 | E30: 0.004613209 | F30: 0.000337606 | G30: 0.061029838
A31: 38017 | B31: ='Final Data'!I31 -> 0.003221353 | C31: ='3.8 Data - CAD#USD '!F32/100 -> 0.013533513 | D31: ='3.8 Data - CAD#USD '!G32/100 -> 0.017435617 | E31: 0.004364981 | F31: -0.00756763 | G31: 0.067017477
A32: 38046 | B32: ='Final Data'!I32 -> 0.0012614679 | C32: ='3.8 Data - CAD#USD '!F33/100 -> 0.013533513 | D32: ='3.8 Data - CAD#USD '!G33/100 -> 0.017435617 | E32: 0.003694746 | F32: -0.009110071 | G32: 0.067017479
A33: 38077 | B33: ='Final Data'!I33 -> 0.0034360325 | C33: ='3.8 Data - CAD#USD '!F34/100 -> 0.013840178 | D33: ='3.8 Data - CAD#USD '!G34/100 -> 0.017481015 | E33: 0.00433912 | F33: -0.010604806 | G33: 0.067017479
A34: 38107 | B34: ='Final Data'!I34 -> 0.032758817 | C34: ='3.8 Data - CAD#USD '!F35/100 -> 0.013840178 | D34: ='3.8 Data - CAD#USD '!G35/100 -> 0.017481015 | E34: 0.002652375 | F34: -0.006308031 | G34: 0.07872937
... A270: 45291 | B270: ='Final Data'!I270 -> -0.020966184 | C270: ='3.8 Data - CAD#USD '!F271/100 -> 0.013030517 | D270: ='3.8 Data - CAD#USD '!G271/100 -> 0.016129425 | E270: -0.00778089 | F270: 0.000500545 | G270: 0.03378605

Sheet 3.8.2 Exchange Risk - EUR
A1: Date | B1: Exchange Rate Returns | C1: GDP Growth - EUR | D1: GDP Growth - USD | E1: {='3.8 Data EUR#USD'!J2:L271} -> Interest Rate Differential | F1: Inflation Rate Differential | G1: Account Balance Differential | I1: SUMMARY OUTPUT
A2: 37134 | C2: ='3.8 Data EUR#USD'!F3/100 -> 0.01497339 | D2: ='3.8 Data EUR#USD'!G3/100 -> 0.012591457 | E2: 0.001170896 | F2: 0.00154095 | G2: 0.033429941
A3: 37164 | B3: ='Final Data'!I3 -> 0.00052900723 | C3: ='3.8 Data EUR#USD'!F4/100 -> 0.01422207 | D3: ='3.8 Data EUR#USD'!G4/100 -> 0.0114197 | E3: 0.00334142 | F3: 0.000147724 | G3: 0.027781604 | I3: Regression Statistics
A4: 37195 | B4: ='Final Data'!I4 -> 0.012160733 | C4: ='3.8 Data EUR#USD'!F5/100 -> 0.01422207 | D4: ='3.8 Data EUR#USD'!G5/100 -> 0.0114197 | E4: 0.002898723 | F4: 0.003309238 | G4: 0.029669333 | I4: Multiple R | J4: 0.2090108
A5: 37225 | B5: ='Final Data'!I5 -> 0.011056939 | C5: ='3.8 Data EUR#USD'!F6/100 -> 0.01422207 | D5: ='3.8 Data EUR#USD'!G6/100 -> 0.0114197 | E5: 0.000616546 | F5: 0.002459277 | G5: 0.027484183 | I5: R Square | J5: 0.043685516
A6: 37256 | B6: ='Final Data'!I6 -> 0.0053388444 | C6: ='3.8 Data EUR#USD'!F7/100 -> 0.013253248 | D6: ='3.8 Data EUR#USD'!G7/100 -> 0.010529206 | E6: -0.001382396 | F6: 0.006407131 | G6: 0.037513241 | I6: Adjusted R Square | J6: 0.02543524
A7: 37287 | B7: ='Final Data'!I7 -> 0.029892934 | C7: ='3.8 Data EUR#USD'!F8/100 -> 0.013253248 | D7: ='3.8 Data EUR#USD'!G8/100 -> 0.010529206 | E7: -2.0283e-05 | F7: 0.005901523 | G7: 0.036850945 | I7: Standard Error | J7: 0.022098846
A8: 37315 | B8: ='Final Data'!I8 -> -0.0089820359 | C8: ='3.8 Data EUR#USD'!F9/100 -> 0.013253248 | D8: ='3.8 Data EUR#USD'!G9/100 -> 0.010529206 | E8: 0.001853296 | F8: 0.004311843 | G8: 0.038125167 | I8: Observations | J8: 268
A9: 37346 | B9: ='Final Data'!I9 -> -0.0045317221 | C9: ='3.8 Data EUR#USD'!F10/100 -> 0.011388061 | D9: ='3.8 Data EUR#USD'!G10/100 -> 0.013270985 | E9: 0.000527656 | F9: 0.003476097 | G9: 0.038496045
A10: 37376 | B10: ='Final Data'!I10 -> -0.028915866 | C10: ='3.8 Data EUR#USD'!F11/100 -> 0.011388061 | D10: ='3.8 Data EUR#USD'!G11/100 -> 0.013270985 | E10: 0.001233749 | F10: 0.000157379 | G10: 0.031347747 | I10: ANOVA
A11: 37407 | B11: ='Final Data'!I11 -> -0.029342825 | C11: ='3.8 Data EUR#USD'!F12/100 -> 0.011388061 | D11: ='3.8 Data EUR#USD'!G12/100 -> 0.013270985 | E11: 0.001874623 | F11: 0.000169491 | G11: 0.042834427 | J11: df | K11: SS | L11: MS | M11: F | N11: Significance F
A12: 37437 | B12: ='Final Data'!I12 -> -0.05097934 | C12: ='3.8 Data EUR#USD'!F13/100 -> 0.012344112 | D12: ='3.8 Data EUR#USD'!G13/100 -> 0.01324841 | E12: 0.002823385 | F12: 0.000440237 | G12: 0.043078126 | I12: Regression | J12: 5 | K12: 0.0058449016 | L12: 0.0011689803 | M12: 2.3936907 | N12: 0.038082756
A13: 37468 | B13: ='Final Data'!I13 -> 0.012251437 | C13: ='3.8 Data EUR#USD'!F14/100 -> 0.012344112 | D13: ='3.8 Data EUR#USD'!G14/100 -> 0.01324841 | E13: 0.003971238 | F13: -0.00282727 | G13: 0.048503061 | I13: Residual | J13: 262 | K13: 0.12795005 | L13: 0.00048835898
A14: 37499 | B14: ='Final Data'!I14 -> -0.0040033516 | C14: ='3.8 Data EUR#USD'!F15/100 -> 0.012344112 | D14: ='3.8 Data EUR#USD'!G15/100 -> 0.01324841 | E14: 0.005202843 | F14: -0.005190874 | G14: 0.048660142 | I14: Total | J14: 267 | K14: 0.13379495
A15: 37529 | B15: ='Final Data'!I15 -> -0.0010282296 | C15: ='3.8 Data EUR#USD'!F16/100 -> 0.012879614 | D15: ='3.8 Data EUR#USD'!G16/100 -> 0.01465356 | E15: 0.006951816 | F15: -0.002894893 | G15: 0.048694735
A16: 37560 | B16: ='Final Data'!I16 -> -0.0021521475 | C16: ='3.8 Data EUR#USD'!F17/100 -> 0.012879614 | D16: ='3.8 Data EUR#USD'!G17/100 -> 0.01465356 | E16: 0.007120067 | F16: -0.005958035 | G16: 0.046798648 | J16: Coefficients | K16: Standard Error | L16: t Stat | M16: P-value | N16: Lower 95% | O16: Upper 95% | P16: Lower 95.0% | Q16: Upper 95.0%
A17: 37590 | B17: ='Final Data'!I17 -> -0.0021567892 | C17: ='3.8 Data EUR#USD'!F18/100 -> 0.012879614 | D17: ='3.8 Data EUR#USD'!G18/100 -> 0.01465356 | E17: 0.00584873 | F17: -0.007700132 | G17: 0.055325947 | I17: Intercept | J17: 0.0038041658 | K17: 0.0064537824 | L17: 0.58944749 | M17: 0.55606906 | N17: -0.0089037171 | O17: 0.016512049 | P17: -0.0089037171 | Q17: 0.016512049
A18: 37621 | B18: ='Final Data'!I18 -> -0.042853115 | C18: ='3.8 Data EUR#USD'!F19/100 -> 0.013324288 | D18: ='3.8 Data EUR#USD'!G19/100 -> 0.014410507 | E18: 0.004203063 | F18: -0.010002493 | G18: 0.039926012 | I18: =C1 -> GDP Growth - EUR | J18: -0.2418871 | K18: 0.26932338 | L18: -0.89812887 | M18: 0.36994146 | N18: -0.77220092 | O18: 0.28842671 | P18: -0.77220092 | Q18: 0.28842671
A19: 37652 | B19: ='Final Data'!I19 -> -0.019047619 | C19: ='3.8 Data EUR#USD'!F20/100 -> 0.013324288 | D19: ='3.8 Data EUR#USD'!G20/100 -> 0.014410507 | E19: 0.002344137 | F19: -0.004871318 | G19: 0.033149491 | I19: =D1 -> GDP Growth - USD | J19: 0.58096857 | K19: 0.33950301 | L19: 1.7112325 | M19: 0.088221725 | N19: -0.087533132 | O19: 1.2494703 | P19: -0.087533132 | Q19: 1.2494703
A20: 37680 | B20: ='Final Data'!I20 -> -0.0020018016 | C20: ='3.8 Data EUR#USD'!F21/100 -> 0.013324288 | D20: ='3.8 Data EUR#USD'!G21/100 -> 0.014410507 | E20: 0.001736507 | F20: -0.007856862 | G20: 0.043145747 | I20: =E1 -> Interest Rate Differential | J20: -0.10167042 | K20: 0.16171993 | L20: -0.62868206 | M20: 0.53010493 | N20: -0.42010661 | O20: 0.21676578 | P20: -0.42010661 | Q20: 0.21676578
A21: 37711 | B21: ='Final Data'!I21 -> -0.0065189048 | C21: ='3.8 Data EUR#USD'!F22/100 -> 0.012340915 | D21: ='3.8 Data EUR#USD'!G22/100 -> 0.013888995 | E21: 0.003202653 | F21: -0.006622839 | G21: 0.03861845 | I21: =F1 -> Inflation Rate Differential | J21: -0.36941202 | K21: 0.15966253 | L21: -2.3137052 | M21: 0.021458199 | N21: -0.68379707 | O21: -0.05502697 | P21: -0.68379707 | Q21: -0.05502697
A22: 37741 | B22: ='Final Data'!I22 -> -0.018877448 | C22: ='3.8 Data EUR#USD'!F23/100 -> 0.012340915 | D22: ='3.8 Data EUR#USD'!G23/100 -> 0.013888995 | E22: 0.003068621 | F22: -0.001810405 | G22: 0.045467451 | I22: =G1 -> Account Balance Differential | J22: -0.20760573 | K22: 0.1204171 | L22: -1.7240552 | M22: 0.08587743 | N22: -0.4447142 | O22: 0.029502731 | P22: -0.4447142 | Q22: 0.029502731
A23: 37772 | B23: ='Final Data'!I23 -> -0.040333368 | C23: ='3.8 Data EUR#USD'!F24/100 -> 0.012340915 | D23: ='3.8 Data EUR#USD'!G24/100 -> 0.013888995 | E23: 0.003999423 | F23: -0.000672949 | G23: 0.047372611
A24: 37802 | B24: ='Final Data'!I24 -> 0.015653479 | C24: ='3.8 Data EUR#USD'!F25/100 -> 0.011405295 | D24: ='3.8 Data EUR#USD'!G25/100 -> 0.014350123 | E24: 0.00438187 | F24: 3.6487e-05 | G24: 0.043438466
A25: 37833 | B25: ='Final Data'!I25 -> 0.022801647 | C25: ='3.8 Data EUR#USD'!F26/100 -> 0.011405295 | D25: ='3.8 Data EUR#USD'!G26/100 -> 0.014350123 | E25: 0.00103297 | F25: -0.002529101 | G25: 0.051087359
A26: 37864 | B26: ='Final Data'!I26 -> 0.012488389 | C26: ='3.8 Data EUR#USD'!F27/100 -> 0.011405295 | D26: ='3.8 Data EUR#USD'!G27/100 -> 0.014350123 | E26: -0.002166146 | F26: -0.002935681 | G26: 0.055798818
A27: 37894 | B27: ='Final Data'!I27 -> -0.05351682 | C27: ='3.8 Data EUR#USD'!F28/100 -> 0.011828886 | D27: ='3.8 Data EUR#USD'!G28/100 -> 0.01617407 | E27: -4.0017e-05 | F27: -0.003826943 | G27: 0.05350649
A28: 37925 | B28: ='Final Data'!I28 -> -0.0012924071 | C28: ='3.8 Data EUR#USD'!F29/100 -> 0.011828886 | D28: ='3.8 Data EUR#USD'!G29/100 -> 0.01617407 | E28: 0.000302817 | F28: -0.000688783 | G28: 0.057101511
A29: 37955 | B29: ='Final Data'!I29 -> -0.027175671 | C29: ='3.8 Data EUR#USD'!F30/100 -> 0.011828886 | D29: ='3.8 Data EUR#USD'!G30/100 -> 0.01617407 | E29: 0.00132526 | F29: 0.001046201 | G29: 0.054971367
A30: 37986 | B30: ='Final Data'!I30 -> -0.036470458 | C30: ='3.8 Data EUR#USD'!F31/100 -> 0.012788176 | D30: ='3.8 Data EUR#USD'!G31/100 -> 0.017435617 | E30: 0.001204706 | F30: -0.001683392 | G30: 0.054665279
A31: 38017 | B31: ='Final Data'!I31 -> 0.003221353 | C31: ='3.8 Data EUR#USD'!F32/100 -> 0.012788176 | D31: ='3.8 Data EUR#USD'!G32/100 -> 0.017435617 | E31: 0.000983027 | F31: -0.002851626 | G31: 0.05504433
A32: 38046 | B32: ='Final Data'!I32 -> 0.0012614679 | C32: ='3.8 Data EUR#USD'!F33/100 -> 0.012788176 | D32: ='3.8 Data EUR#USD'!G33/100 -> 0.017435617 | E32: 0.001288256 | F32: -0.000343249 | G32: 0.059994046
A33: 38077 | B33: ='Final Data'!I33 -> 0.0034360325 | C33: ='3.8 Data EUR#USD'!F34/100 -> 0.014239898 | D33: ='3.8 Data EUR#USD'!G34/100 -> 0.017481015 | E33: 0.002118443 | F33: -0.001257346 | G33: 0.063603603
A34: 38107 | B34: ='Final Data'!I34 -> 0.032758817 | C34: ='3.8 Data EUR#USD'!F35/100 -> 0.014239898 | D34: ='3.8 Data EUR#USD'!G35/100 -> 0.017481015 | E34: -0.001219735 | F34: -0.003584766 | G34: 0.065652598
... A270: 45291 | B270: ='Final Data'!I270 -> -0.020966184 | C270: ='3.8 Data EUR#USD'!F271/100 -> 0.010687455 | D270: ='3.8 Data EUR#USD'!G271/100 -> 0.016129425 | E270: -0.01323112 | F270: -0.003926386 | G270: 0.0653249

Sheet 3.7-9 Prediction and Hedging
A1: Date | B1: {='Final Data'!P1:R1} -> ADP Returns | C1: S&P500 Returns | D1: Exchange Rate Returns | E1: Rf (monthly) | G1: Enriched Capital Asset Pricing Model
A2: 45322 | E2: =('Final Data'!M2/12/100) -> 0.0046083333 | G2: Cumulative S&P500 Returns | H2: {=PRODUCT(1+C3:C13)-1} -> 0.21379588
A3: 45351 | B3: {='Final Data'!P3:R13} -> 0.021767434 | C3: 0.051720615 | D3: 0.0086181853 | E3: ='Final Data'!M3/100/12 -> 0.0046083333 | G3: Cumulative Exchange Rate Returns | H3: {=PRODUCT(1+D3:D13)-1} -> 0.05054711
A4: 45382 | B4: -0.0055349819 | C4: 0.031018765 | D4: 0.0037442396 | E4: ='Final Data'!M4/100/12 -> 0.004575 | G4: Cumulative Risk-free Rate | H4: {=PRODUCT(1+E3:E13)-1} -> 0.048712392
A5: 45412 | B5: -0.03143269 | C5: -0.041615043 | D5: 0.015973219 | E5: ='Final Data'!M5/100/12 -> 0.0045666667
A6: 45443 | B6: 0.012526355 | C6: 0.048021224 | D6: -0.014592355 | E6: ='Final Data'!M6/100/12 -> 0.0045666667 | G6: α | H6: ='3.4 Regression Model'!G17 -> 0.0014027284
A7: 45473 | B7: -0.025436877 | C7: 0.034669759 | D7: 0.011464603 | E7: ='Final Data'!M7/100/12 -> 0.0045583333 | G7: βMkt | H7: ='3.4 Regression Model'!G18 -> 0.94109413
A8: 45504 | B8: 0.10025556 | C8: 0.011321349 | D8: -0.016718617 | E8: ='Final Data'!M8/100/12 -> 0.004575 | G8: βFX | H8: ='3.4 Regression Model'!G19 -> 0.42908716
A9: 45535 | B9: 0.050605438 | C9: 0.022834688 | D9: -0.023054755 | E9: ='Final Data'!M9/100/12 -> 0.0045083333
A10: 45565 | B10: 0.0029719836 | C10: 0.02019687 | D10: -0.0090462144 | E10: ='Final Data'!M10/100/12 -> 0.0041083333 | G10: ADP Excess Returns | H10: =H6+H7*(H2-H4)+H8*H3 -> 0.17845094
A11: 45596 | B11: 0.045206519 | C11: -0.0098967806 | D11: 0.031752332 | E11: ='Final Data'!M11/100/12 -> 0.0039666667 | G11: ADP Predicted Returns | H11: =H10+H4 -> 0.22716334
A12: 45626 | B12: 0.061160282 | C12: 0.057301352 | D12: 0.016926332 | E12: ='Final Data'!M12/100/12 -> 0.0039666667
A13: 45657 | B13: -0.046264621 | C13: -0.024990137 | D13: 0.026007187 | E13: ='Final Data'!M13/100/12 -> 0.0036666667 | G13: ADP Actual Returns | H13: {=PRODUCT(1+B3:B13)-1} -> 0.19102449
G15: Prediction Error (%) | H15: =(H13-H11)*100 -> -3.6138842
G17: Hedging Strategies
G18: βFX | H18: =H8 -> 0.42908716
G19: Unhedged Value (Investment Value) | H19: 1000000
G21: Contract size | H21: 1000
G22: Index value | H22: 97.18
G23: ICE Future Contact Value | H23: =H21*H22 -> 97180
G25: Hedge ratio | H25: =H18*H19/H23 -> 4.4153854

Sheet 3.4 Regression Model
A1: Date | B1: Stock Excess Returns | C1: Market Excess Returns | D1: Exchange Rate Returns | F1: SUMMARY OUTPUT
A2: 37134
A3: 37164 | B3: ='Final Data'!G3-'Final Data'!D3 -> -0.093090108 | C3: ='Final Data'!H3-'Final Data'!D3 -> -0.083674876 | D3: ='Final Data'!I3 -> 0.00052900723 | F3: Regression Statistics
A4: 37195 | B4: ='Final Data'!G4-'Final Data'!D4 -> 0.096422619 | C4: ='Final Data'!H4-'Final Data'!D4 -> 0.016365697 | D4: ='Final Data'!I4 -> 0.012160733 | F4: Multiple R | G4: 0.65420583
A5: 37225 | B5: ='Final Data'!G5-'Final Data'!D5 -> 0.071999545 | C5: ='Final Data'!H5-'Final Data'!D5 -> 0.073644535 | D5: ='Final Data'!I5 -> 0.011056939 | F5: R Square | G5: 0.42798527
A6: 37256 | B6: ='Final Data'!G6-'Final Data'!D6 -> 0.060626686 | C6: ='Final Data'!H6-'Final Data'!D6 -> 0.0061471698 | D6: ='Final Data'!I6 -> 0.0053388444 | F6: Adjusted R Square | G6: 0.42366818
A7: 37287 | B7: ='Final Data'!G7-'Final Data'!D7 -> -0.084600184 | C7: ='Final Data'!H7-'Final Data'!D7 -> -0.01699931 | D7: ='Final Data'!I7 -> 0.029892934 | F7: Standard Error | G7: 0.044975634
A8: 37315 | B8: ='Final Data'!G8-'Final Data'!D8 -> -0.025355556 | C8: ='Final Data'!H8-'Final Data'!D8 -> -0.022259447 | D8: ='Final Data'!I8 -> -0.0089820359 | F8: Observations | G8: 268
A9: 37346 | B9: ='Final Data'!G9-'Final Data'!D9 -> 0.10401616 | C9: ='Final Data'!H9-'Final Data'!D9 -> 0.035309334 | D9: ='Final Data'!I9 -> -0.0045317221
A10: 37376 | B10: ='Final Data'!G10-'Final Data'!D10 -> -0.12898487 | C10: ='Final Data'!H10-'Final Data'!D10 -> -0.062918263 | D10: ='Final Data'!I10 -> -0.028915866 | F10: ANOVA
A11: 37407 | B11: ='Final Data'!G11-'Final Data'!D11 -> 0.019809782 | C11: ='Final Data'!H11-'Final Data'!D11 -> -0.010533528 | D11: ='Final Data'!I11 -> -0.029342825 | G11: df | H11: SS | I11: MS | J11: F | K11: Significance F
A12: 37437 | B12: ='Final Data'!G12-'Final Data'!D12 -> -0.16261789 | C12: ='Final Data'!H12-'Final Data'!D12 -> -0.073847655 | D12: ='Final Data'!I12 -> -0.05097934 | F12: Regression | G12: 2 | H12: 0.40107175 | I12: 0.20053588 | J12: 99.137391 | K12: 7.1854808e-33
A13: 37468 | B13: ='Final Data'!G13-'Final Data'!D13 -> -0.14518449 | C13: ='Final Data'!H13-'Final Data'!D13 -> -0.080447526 | D13: ='Final Data'!I13 -> 0.012251437 | F13: Residual | G13: 265 | H13: 0.53604404 | I13: 0.0020228077
A14: 37499 | B14: ='Final Data'!G14-'Final Data'!D14 -> 0.011455417 | C14: ='Final Data'!H14-'Final Data'!D14 -> 0.0035197089 | D14: ='Final Data'!I14 -> -0.0040033516 | F14: Total | G14: 267 | H14: 0.93711579
A15: 37529 | B15: ='Final Data'!G15-'Final Data'!D15 -> -0.080761451 | C15: ='Final Data'!H15-'Final Data'!D15 -> -0.11136499 | D15: ='Final Data'!I15 -> -0.0010282296
A16: 37560 | B16: ='Final Data'!G16-'Final Data'!D16 -> 0.22194757 | C16: ='Final Data'!H16-'Final Data'!D16 -> 0.085237904 | D16: ='Final Data'!I16 -> -0.0021521475 | G16: Coefficients | H16: Standard Error | I16: t Stat | J16: P-value | K16: Lower 95% | L16: Upper 95% | M16: Lower 95.0% | N16: Upper 95.0%
A17: 37590 | B17: ='Final Data'!G17-'Final Data'!D17 -> 0.021060379 | C17: ='Final Data'!H17-'Final Data'!D17 -> 0.055968945 | D17: ='Final Data'!I17 -> -0.0021567892 | F17: Intercept | G17: 0.0014027284 | H17: 0.00276876 | I17: 0.50662692 | J17: 0.61283788 | K17: -0.0040488391 | L17: 0.0068542958 | M17: -0.0040488391 | N17: 0.0068542958
A18: 37621 | B18: ='Final Data'!G18-'Final Data'!D18 -> -0.098078445 | C18: ='Final Data'!H18-'Final Data'!D18 -> -0.061343907 | D18: ='Final Data'!I18 -> -0.042853115 | F18: =C1 -> Market Excess Returns | G18: 0.94109413 | H18: 0.067698156 | I18: 13.901326 | J18: 2.2887211e-33 | K18: 0.80779942 | L18: 1.0743888 | M18: 0.80779942 | N18: 1.0743888
A19: 37652 | B19: ='Final Data'!G19-'Final Data'!D19 -> -0.1176629 | C19: ='Final Data'!H19-'Final Data'!D19 -> -0.028367589 | D19: ='Final Data'!I19 -> -0.019047619 | F19: =D1 -> Exchange Rate Returns | G19: 0.42908716 | H19: 0.13300075 | I19: 3.226201 | J19: 0.0014120542 | K19: 0.16721449 | L19: 0.69095982 | M19: 0.16721449 | N19: 0.69095982
A20: 37680 | B20: ='Final Data'!G20-'Final Data'!D20 -> -0.063598469 | C20: ='Final Data'!H20-'Final Data'!D20 -> -0.018070388 | D20: ='Final Data'!I20 -> -0.0020018016
A21: 37711 | B21: ='Final Data'!G21-'Final Data'!D21 -> -0.053582051 | C21: ='Final Data'!H21-'Final Data'!D21 -> 0.0074746602 | D21: ='Final Data'!I21 -> -0.0065189048
A22: 37741 | B22: ='Final Data'!G22-'Final Data'!D22 -> 0.091296073 | C22: ='Final Data'!H22-'Final Data'!D22 -> 0.080053382 | D22: ='Final Data'!I22 -> -0.018877448
A23: 37772 | B23: ='Final Data'!G23-'Final Data'!D23 -> 0.036797235 | C23: ='Final Data'!H23-'Final Data'!D23 -> 0.049965823 | D23: ='Final Data'!I23 -> -0.040333368
A24: 37802 | B24: ='Final Data'!G24-'Final Data'!D24 -> -0.030474427 | C24: ='Final Data'!H24-'Final Data'!D24 -> 0.010636748 | D24: ='Final Data'!I24 -> 0.015653479
A25: 37833 | B25: ='Final Data'!G25-'Final Data'!D25 -> 0.094339127 | C25: ='Final Data'!H25-'Final Data'!D25 -> 0.015455109 | D25: ='Final Data'!I25 -> 0.022801647
A26: 37864 | B26: ='Final Data'!G26-'Final Data'!D26 -> 0.0755048 | C26: ='Final Data'!H26-'Final Data'!D26 -> 0.017056705 | D26: ='Final Data'!I26 -> 0.012488389
A27: 37894 | B27: ='Final Data'!G27-'Final Data'!D27 -> -0.10245389 | C27: ='Final Data'!H27-'Final Data'!D27 -> -0.012629762 | D27: ='Final Data'!I27 -> -0.05351682
A28: 37925 | B28: ='Final Data'!G28-'Final Data'!D28 -> 0.051919665 | C28: ='Final Data'!H28-'Final Data'!D28 -> 0.054119679 | D28: ='Final Data'!I28 -> -0.0012924071
A29: 37955 | B29: ='Final Data'!G29-'Final Data'!D29 -> 0.012183572 | C29: ='Final Data'!H29-'Final Data'!D29 -> 0.0063380984 | D29: ='Final Data'!I29 -> -0.027175671
A30: 37986 | B30: ='Final Data'!G30-'Final Data'!D30 -> 0.035347306 | C30: ='Final Data'!H30-'Final Data'!D30 -> 0.049996551 | D30: ='Final Data'!I30 -> -0.036470458
A31: 38017 | B31: ='Final Data'!G31-'Final Data'!D31 -> 0.078564578 | C31: ='Final Data'!H31-'Final Data'!D31 -> 0.016559407 | D31: ='Final Data'!I31 -> 0.003221353
... A270: 45291 | B270: ='Final Data'!G270-'Final Data'!D270 -> 0.008598817 | C270: ='Final Data'!H270-'Final Data'!D270 -> 0.039562503 | D270: ='Final Data'!I270 -> -0.020966184

Sheet Final Data
A1: Date | B1: DXY | C1: RF (%, annualized) | D1: RF (monthly compounded) | E1: SP500 | F1: ADP | G1: ADP Returns | H1: S&P500 Returns | I1: Exchange Rate Returns | K1: Date | L1: DXY | M1: RF (%, annualized) | N1: SP500 | O1: ADP | P1: ADP Returns | Q1: S&P500 Returns | R1: Exchange Rate Returns
A2: 37134 | B2: 113.42 | C2: 3.4 | D2: =C2/12/100 -> 0.0028333333 | E2: 1133.6 | F2: 51.76 | K2: 45322 | L2: 103.27 | M2: 5.53 | N2: 4845.65 | O2: 245.78
A3: 37164 | B3: 113.48 | C3: 2.28 | D3: =C3/12/100 -> 0.0019 | E3: 1040.9 | F3: 47.04 | G3: =(F3-F2)/F2 -> -0.091190108 | H3: =(E3-E2)/E2 -> -0.081774876 | I3: =(B3-B2)/B2 -> 0.00052900723 | K3: 45351 | L3: 104.16 | M3: 5.53 | N3: 5096.27 | O3: 251.13 | P3: =(O3-O2)/O2 -> 0.021767434 | Q3: =(N3-N2)/N2 -> 0.051720615 | R3: =(L3-L2)/L2 -> 0.0086181853
A4: 37195 | B4: 114.86 | C4: 2.15 | D4: =C4/12/100 -> 0.0017916667 | E4: 1059.8 | F4: 51.66 | G4: =(F4-F3)/F3 -> 0.098214286 | H4: =(E4-E3)/E3 -> 0.018157364 | I4: =(B4-B3)/B3 -> 0.012160733 | K4: 45382 | L4: 104.55 | M4: 5.49 | N4: 5254.35 | O4: 249.74 | P4: =(O4-O3)/O3 -> -0.0055349819 | Q4: =(N4-N3)/N3 -> 0.031018765 | R4: =(L4-L3)/L3 -> 0.0037442396
A5: 37225 | B5: 116.13 | C5: 1.87 | D5: =C5/12/100 -> 0.0015583333 | E5: 1139.5 | F5: 55.46 | G5: =(F5-F4)/F4 -> 0.073557878 | H5: =(E5-E4)/E4 -> 0.075202868 | I5: =(B5-B4)/B4 -> 0.011056939 | K5: 45412 | L5: 106.22 | M5: 5.48 | N5: 5035.69 | O5: 241.89 | P5: =(O5-O4)/O4 -> -0.03143269 | Q5: =(N5-N4)/N4 -> -0.041615043 | R5: =(L5-L4)/L4 -> 0.015973219
A6: 37256 | B6: 116.75 | C6: 1.68 | D6: =C6/12/100 -> 0.0014 | E6: 1148.1 | F6: 58.9 | G6: =(F6-F5)/F5 -> 0.062026686 | H6: =(E6-E5)/E5 -> 0.0075471698 | I6: =(B6-B5)/B5 -> 0.0053388444 | K6: 45443 | L6: 104.67 | M6: 5.48 | N6: 5277.51 | O6: 244.92 | P6: =(O6-O5)/O5 -> 0.012526355 | Q6: =(N6-N5)/N5 -> 0.048021224 | R6: =(L6-L5)/L5 -> -0.014592355
A7: 37287 | B7: 120.24 | C7: 1.69 | D7: =C7/12/100 -> 0.0014083333 | E7: 1130.2 | F7: 54 | G7: =(F7-F6)/F6 -> -0.083191851 | H7: =(E7-E6)/E6 -> -0.015590976 | I7: =(B7-B6)/B6 -> 0.029892934 | K7: 45473 | L7: 105.87 | M7: 5.47 | N7: 5460.48 | O7: 238.69 | P7: =(O7-O6)/O6 -> -0.025436877 | Q7: =(N7-N6)/N6 -> 0.034669759 | R7: =(L7-L6)/L6 -> 0.011464603
A8: 37315 | B8: 119.16 | C8: 1.76 | D8: =C8/12/100 -> 0.0014666667 | E8: 1106.7 | F8: 52.71 | G8: =(F8-F7)/F7 -> -0.023888889 | H8: =(E8-E7)/E7 -> -0.02079278 | I8: =(B8-B7)/B7 -> -0.0089820359 | K8: 45504 | L8: 104.1 | M8: 5.49 | N8: 5522.3 | O8: 262.62 | P8: =(O8-O7)/O7 -> 0.10025556 | Q8: =(N8-N7)/N7 -> 0.011321349 | R8: =(L8-L7)/L7 -> -0.016718617
A9: 37346 | B9: 118.62 | C9: 1.76 | D9: =C9/12/100 -> 0.0014666667 | E9: 1147.4 | F9: 58.27 | G9: =(F9-F8)/F8 -> 0.10548283 | H9: =(E9-E8)/E8 -> 0.036776001 | I9: =(B9-B8)/B8 -> -0.0045317221 | K9: 45535 | L9: 101.7 | M9: 5.41 | N9: 5648.4 | O9: 275.91 | P9: =(O9-O8)/O8 -> 0.050605438 | Q9: =(N9-N8)/N8 -> 0.022834688 | R9: =(L9-L8)/L8 -> -0.023054755
A10: 37376 | B10: 115.19 | C10: 1.77 | D10: =C10/12/100 -> 0.001475 | E10: 1076.9 | F10: 50.84 | G10: =(F10-F9)/F9 -> -0.12750987 | H10: =(E10-E9)/E9 -> -0.061443263 | I10: =(B10-B9)/B9 -> -0.028915866 | K10: 45565 | L10: 100.78 | M10: 4.93 | N10: 5762.48 | O10: 276.73 | P10: =(O10-O9)/O9 -> 0.0029719836 | Q10: =(N10-N9)/N9 -> 0.02019687 | R10: =(L10-L9)/L9 -> -0.0090462144
A11: 37407 | B11: 111.81 | C11: 1.72 | D11: =C11/12/100 -> 0.0014333333 | E11: 1067.1 | F11: 51.92 | G11: =(F11-F10)/F10 -> 0.021243116 | H11: =(E11-E10)/E10 -> -0.009100195 | I11: =(B11-B10)/B10 -> -0.029342825 | K11: 45596 | L11: 103.98 | M11: 4.76 | N11: 5705.45 | O11: 289.24 | P11: =(O11-O10)/O10 -> 0.045206519 | Q11: =(N11-N10)/N10 -> -0.0098967806 | R11: =(L11-L10)/L10 -> 0.031752332
A12: 37437 | B12: 106.11 | C12: 1.69 | D12: =C12/12/100 -> 0.0014083333 | E12: 989.8 | F12: 43.55 | G12: =(F12-F11)/F11 -> -0.16120955 | H12: =(E12-E11)/E11 -> -0.072439322 | I12: =(B12-B11)/B11 -> -0.05097934 | K12: 45626 | L12: 105.74 | M12: 4.76 | N12: 6032.38 | O12: 306.93 | P12: =(O12-O11)/O11 -> 0.061160282 | Q12: =(N12-N11)/N11 -> 0.057301352 | R12: =(L12-L11)/L11 -> 0.016926332
A13: 37468 | B13: 107.41 | C13: 1.73 | D13: =C13/12/100 -> 0.0014416667 | E13: 911.6 | F13: 37.29 | G13: =(F13-F12)/F12 -> -0.14374282 | H13: =(E13-E12)/E12 -> -0.07900586 | I13: =(B13-B12)/B12 -> 0.012251437 | K13: 45657 | L13: 108.49 | M13: 4.4 | N13: 5881.63 | O13: 292.73 | P13: =(O13-O12)/O12 -> -0.046264621 | Q13: =(N13-N12)/N12 -> -0.024990137 | R13: =(L13-L12)/L12 -> 0.026007187
A14: 37499 | B14: 106.98 | C14: 1.7 | D14: =C14/12/100 -> 0.0014166667 | E14: 916.1 | F14: 37.77 | G14: =(F14-F13)/F13 -> 0.012872084 | H14: =(E14-E13)/E13 -> 0.0049363756 | I14: =(B14-B13)/B13 -> -0.0040033516
A15: 37529 | B15: 106.87 | C15: 1.6 | D15: =C15/12/100 -> 0.0013333333 | E15: 815.3 | F15: 34.77 | G15: =(F15-F14)/F14 -> -0.079428118 | H15: =(E15-E14)/E14 -> -0.11003166 | I15: =(B15-B14)/B14 -> -0.0010282296
A16: 37560 | B16: 106.64 | C16: 1.48 | D16: =C16/12/100 -> 0.0012333333 | E16: 885.8 | F16: 42.53 | G16: =(F16-F15)/F15 -> 0.2231809 | H16: =(E16-E15)/E15 -> 0.086471238 | I16: =(B16-B15)/B15 -> -0.0021521475
A17: 37590 | B17: 106.41 | C17: 1.25 | D17: =C17/12/100 -> 0.0010416667 | E17: 936.3 | F17: 43.47 | G17: =(F17-F16)/F16 -> 0.022102046 | H17: =(E17-E16)/E16 -> 0.057010612 | I17: =(B17-B16)/B16 -> -0.0021567892
A18: 37621 | B18: 101.85 | C18: 1.2 | D18: =C18/12/100 -> 0.001 | E18: 879.8 | F18: 39.25 | G18: =(F18-F17)/F17 -> -0.097078445 | H18: =(E18-E17)/E17 -> -0.060343907 | I18: =(B18-B17)/B17 -> -0.042853115
A19: 37652 | B19: 99.91 | C19: 1.17 | D19: =C19/12/100 -> 0.000975 | E19: 855.7 | F19: 34.67 | G19: =(F19-F18)/F18 -> -0.1166879 | H19: =(E19-E18)/E18 -> -0.027392589 | I19: =(B19-B18)/B18 -> -0.019047619
A20: 37680 | B20: 99.71 | C20: 1.21 | D20: =C20/12/100 -> 0.0010083333 | E20: 841.1 | F20: 32.5 | G20: =(F20-F19)/F19 -> -0.062590136 | H20: =(E20-E19)/E19 -> -0.017062054 | I20: =(B20-B19)/B19 -> -0.0020018016
A21: 37711 | B21: 99.06 | C21: 1.16 | D21: =C21/12/100 -> 0.00096666667 | E21: 848.2 | F21: 30.79 | G21: =(F21-F20)/F20 -> -0.052615385 | H21: =(E21-E20)/E20 -> 0.0084413268 | I21: =(B21-B20)/B20 -> -0.0065189048
A22: 37741 | B22: 97.19 | C22: 1.13 | D22: =C22/12/100 -> 0.00094166667 | E22: 916.9 | F22: 33.63 | G22: =(F22-F21)/F21 -> 0.09223774 | H22: =(E22-E21)/E21 -> 0.080995048 | I22: =(B22-B21)/B21 -> -0.018877448
A23: 37772 | B23: 93.27 | C23: 1.16 | D23: =C23/12/100 -> 0.00096666667 | E23: 963.6 | F23: 34.9 | G23: =(F23-F22)/F22 -> 0.037763901 | H23: =(E23-E22)/E22 -> 0.05093249 | I23: =(B23-B22)/B22 -> -0.040333368
A24: 37802 | B24: 94.73 | C24: 0.81 | D24: =C24/12/100 -> 0.000675 | E24: 974.5 | F24: 33.86 | G24: =(F24-F23)/F23 -> -0.029799427 | H24: =(E24-E23)/E23 -> 0.011311748 | I24: =(B24-B23)/B23 -> 0.015653479
A25: 37833 | B25: 96.89 | C25: 0.91 | D25: =C25/12/100 -> 0.00075833333 | E25: 990.3 | F25: 37.08 | G25: =(F25-F24)/F24 -> 0.09509746 | H25: =(E25-E24)/E24 -> 0.016213443 | I25: =(B25-B24)/B24 -> 0.022801647
... A270: 45291 | B270: 101.33 | C270: 5.6 | D270: =C270/12/100 -> 0.0046666667 | E270: 4769.83 | F270: 232.97 | G270: =(F270-F269)/F269 -> 0.013265484 | H270: =(E270-E269)/E269 -> 0.044229169 | I270: =(B270-B269)/B269 -> -0.020966184
H271: {=PRODUCT(1+H259:H270)-1} -> 0.24230499 | I271: {=PRODUCT(1+I259:I270)-1} -> -0.021155332

Sheet 3.8 Data - CAD#USD 
B1: Long-term Interest Rate | D1: Inflation Rate (CPI) | F1: Real GDP Growth | H1: Account Balance
A2: Date | B2: CAD | C2: USD | D2: CAD | E2: USD | F2: CAD | G2: USD | H2: CAD | I2: USD | J2: Interest Rate Differential | K2: Inflation Rate Differential | L2: Account Balance Differential
A3: 37134 | B3: 5.53091 | C3: 4.9713054 | D3: 2.8272295 | E3: 2.721485 | F3: 1.4604127 | G3: 1.2591457 | H3: 1.4401073 | I3: -3.9039369 | J3: =(B3-C3)/100 -> 0.005596046 | K3: =(D3-E3)/100 -> 0.001057445 | L3: =(H3-I3)/100 -> 0.053440442
A4: 37164 | B4: 5.330667 | C4: 4.748667 | D4: 2.6068785 | E4: 2.5921676 | F4: 1.2615182 | G4: 1.14197 | H4: 1.4401072 | I4: -3.9039369 | J4: =(B4-C4)/100 -> 0.00582 | K4: =(D4-E4)/100 -> 0.000147109 | L4: =(H4-I4)/100 -> 0.053440441
A5: 37195 | B5: 5.2327275 | C5: 4.564782 | D5: 1.8691618 | E5: 2.127676 | F5: 1.2615182 | G5: 1.14197 | H5: 1.1307567 | I5: -3.3117878 | J5: =(B5-C5)/100 -> 0.006679455 | K5: =(D5-E5)/100 -> -0.002585142 | L5: =(H5-I5)/100 -> 0.044425445
A6: 37225 | B6: 5.1629996 | C6: 4.6366677 | D6: 0.6198329 | E6: 1.8943809 | F6: 1.2615182 | G6: 1.14197 | H6: 1.1307567 | I6: -3.3117878 | J6: =(B6-C6)/100 -> 0.005263319 | K6: =(D6-E6)/100 -> -0.01274548 | L6: =(H6-I6)/100 -> 0.044425445
A7: 37256 | B7: 5.4084215 | C7: 5.0875006 | D7: 0.72165155 | E7: 1.6036576 | F7: 1.3412488 | G7: 1.0529206 | H7: 1.1307567 | I7: -3.3117878 | J7: =(B7-C7)/100 -> 0.003209209 | K7: =(D7-E7)/100 -> -0.0088200605 | L7: =(H7-I7)/100 -> 0.044425445
A8: 37287 | B8: 5.345714 | C8: 5.035714 | D8: 1.3429754 | E8: 1.1958938 | F8: 1.3412488 | G8: 1.0529206 | H8: 2.4466617 | I8: -3.8061113 | J8: =(B8-C8)/100 -> 0.0031 | K8: =(D8-E8)/100 -> 0.001470816 | L8: =(H8-I8)/100 -> 0.06252773
A9: 37315 | B9: 5.32158 | C9: 4.911579 | D9: 1.5479872 | E9: 1.1363616 | F9: 1.3412488 | G9: 1.0529206 | H9: 2.4466615 | I9: -3.8061113 | J9: =(B9-C9)/100 -> 0.00410001 | K9: =(D9-E9)/100 -> 0.004116256 | L9: =(H9-I9)/100 -> 0.062527728
A10: 37346 | B10: 5.667 | C10: 5.2839994 | D10: 1.7507797 | E10: 1.3628697 | F10: 1.4917686 | G10: 1.3270985 | H10: 2.4466615 | I10: -3.8061113 | J10: =(B10-C10)/100 -> 0.003830006 | K10: =(D10-E10)/100 -> 0.0038791 | L10: =(H10-I10)/100 -> 0.062527728
A11: 37376 | B11: 5.6586366 | C11: 5.2109094 | D11: 1.7382486 | E11: 1.6439961 | F11: 1.4917686 | G11: 1.3270985 | H11: 1.863576 | I11: -4.2128835 | J11: =(B11-C11)/100 -> 0.004477272 | K11: =(D11-E11)/100 -> 0.000942525 | L11: =(H11-I11)/100 -> 0.060764595
A12: 37407 | B12: 5.59619 | C12: 5.164546 | D12: 1.0162654 | E12: 1.2408334 | F12: 1.4917686 | G12: 1.3270985 | H12: 1.863576 | I12: -4.2128835 | J12: =(B12-C12)/100 -> 0.00431644 | K12: =(D12-E12)/100 -> -0.00224568 | L12: =(H12-I12)/100 -> 0.060764595
A13: 37437 | B13: 5.4240007 | C13: 4.926499 | D13: 1.2195168 | E13: 1.0692196 | F13: 1.5328482 | G13: 1.324841 | H13: 1.863576 | I13: -4.2128835 | J13: =(B13-C13)/100 -> 0.004975017 | K13: =(D13-E13)/100 -> 0.001502972 | L13: =(H13-I13)/100 -> 0.060764595
A14: 37468 | B14: 5.287143 | C14: 4.6531825 | D14: 2.2426112 | E14: 1.4656144 | F14: 1.5328482 | G14: 1.324841 | H14: 1.4038188 | I14: -4.1825776 | J14: =(B14-C14)/100 -> 0.006339605 | K14: =(D14-E14)/100 -> 0.007769968 | L14: =(H14-I14)/100 -> 0.055863964
... A271: 45291 | B271: 3.240015 | C271: 4.018104 | D271: 3.3722441 | E271: 3.3221896 | F271: 1.3030517 | G271: 1.6129425 | H271: -0.07408604 | I271: -3.452691 | J271: =(B271-C271)/100 -> -0.00778089 | K271: =(D271-E271)/100 -> 0.000500545 | L271: =(H271-I271)/100 -> 0.03378605

Sheet 3.8 Data EUR#USD
B1: Long-term Interest Rate | D1: Inflation Rate (CPI) | F1: Real GDP Growth | H1: Account Balance
A2: Date | B2: EUR | C2: USD | D2: EUR | E2: USD | F2: EUR | G2: USD | H2: EUR | I2: USD | J2: Interest Rate Differential | K2: Inflation Rate Differential | L2: Account Balance Differential
A3: 37134 | B3: 5.088395 | C3: 4.9713054 | D3: 2.87558 | E3: 2.721485 | F3: 1.497339 | G3: 1.2591457 | H3: -0.5609428 | I3: -3.9039369 | J3: =(B3-C3)/100 -> 0.001170896 | K3: =(D3-E3)/100 -> 0.00154095 | L3: =(H3-I3)/100 -> 0.033429941
A4: 37164 | B4: 5.082809 | C4: 4.748667 | D4: 2.60694 | E4: 2.5921676 | F4: 1.422207 | G4: 1.14197 | H4: -1.1257765 | I4: -3.9039369 | J4: =(B4-C4)/100 -> 0.00334142 | K4: =(D4-E4)/100 -> 0.000147724 | L4: =(H4-I4)/100 -> 0.027781604
A5: 37195 | B5: 4.8546543 | C5: 4.564782 | D5: 2.4585998 | E5: 2.127676 | F5: 1.422207 | G5: 1.14197 | H5: -0.3448545 | I5: -3.3117878 | J5: =(B5-C5)/100 -> 0.002898723 | K5: =(D5-E5)/100 -> 0.003309238 | L5: =(H5-I5)/100 -> 0.029669333
A6: 37225 | B6: 4.6983223 | C6: 4.6366677 | D6: 2.1403086 | E6: 1.8943809 | F6: 1.422207 | G6: 1.14197 | H6: -0.56336945 | I6: -3.3117878 | J6: =(B6-C6)/100 -> 0.000616546 | K6: =(D6-E6)/100 -> 0.002459277 | L6: =(H6-I6)/100 -> 0.027484183
A7: 37256 | B7: 4.949261 | C7: 5.0875006 | D7: 2.2443707 | E7: 1.6036576 | F7: 1.3253248 | G7: 1.0529206 | H7: 0.4395363 | I7: -3.3117878 | J7: =(B7-C7)/100 -> -0.001382396 | K7: =(D7-E7)/100 -> 0.006407131 | L7: =(H7-I7)/100 -> 0.037513241
A8: 37287 | B8: 5.0336857 | C8: 5.035714 | D8: 1.7860461 | E8: 1.1958938 | F8: 1.3253248 | G8: 1.0529206 | H8: -0.12101681 | I8: -3.8061113 | J8: =(B8-C8)/100 -> -2.0283e-05 | K8: =(D8-E8)/100 -> 0.005901523 | L8: =(H8-I8)/100 -> 0.036850945
A9: 37315 | B9: 5.0969086 | C9: 4.911579 | D9: 1.5675459 | E9: 1.1363616 | F9: 1.3253248 | G9: 1.0529206 | H9: 0.0064054187 | I9: -3.8061113 | J9: =(B9-C9)/100 -> 0.001853296 | K9: =(D9-E9)/100 -> 0.004311843 | L9: =(H9-I9)/100 -> 0.038125167
A10: 37346 | B10: 5.336765 | C10: 5.2839994 | D10: 1.7104794 | E10: 1.3628697 | F10: 1.1388061 | G10: 1.3270985 | H10: 0.043493178 | I10: -3.8061113 | J10: =(B10-C10)/100 -> 0.000527656 | K10: =(D10-E10)/100 -> 0.003476097 | L10: =(H10-I10)/100 -> 0.038496045
A11: 37376 | B11: 5.3342843 | C11: 5.2109094 | D11: 1.659734 | E11: 1.6439961 | F11: 1.1388061 | G11: 1.3270985 | H11: -1.0781088 | I11: -4.2128835 | J11: =(B11-C11)/100 -> 0.001233749 | K11: =(D11-E11)/100 -> 0.000157379 | L11: =(H11-I11)/100 -> 0.031347747
A12: 37407 | B12: 5.3520083 | C12: 5.164546 | D12: 1.2577825 | E12: 1.2408334 | F12: 1.1388061 | G12: 1.3270985 | H12: 0.07055924 | I12: -4.2128835 | J12: =(B12-C12)/100 -> 0.001874623 | K12: =(D12-E12)/100 -> 0.000169491 | L12: =(H12-I12)/100 -> 0.042834427
A13: 37437 | B13: 5.2088375 | C13: 4.926499 | D13: 1.1132433 | E13: 1.0692196 | F13: 1.2344112 | G13: 1.324841 | H13: 0.09492914 | I13: -4.2128835 | J13: =(B13-C13)/100 -> 0.002823385 | K13: =(D13-E13)/100 -> 0.000440237 | L13: =(H13-I13)/100 -> 0.043078126
A14: 37468 | B14: 5.0503063 | C14: 4.6531825 | D14: 1.1828874 | E14: 1.4656144 | F14: 1.2344112 | G14: 1.324841 | H14: 0.66772854 | I14: -4.1825776 | J14: =(B14-C14)/100 -> 0.003971238 | K14: =(D14-E14)/100 -> -0.00282727 | L14: =(H14-I14)/100 -> 0.048503061
... A271: 45291 | B271: 2.694992 | C271: 4.018104 | D271: 2.929551 | E271: 3.3221896 | F271: 1.0687455 | G271: 1.6129425 | H271: 3.079799 | I271: -3.452691 | J271: =(B271-C271)/100 -> -0.01323112 | K271: =(D271-E271)/100 -> -0.003926386 | L271: =(H271-I271)/100 -> 0.0653249
